flake8_boolean_trap.py
flake8_boolean_trap-1.0.1.dist-info/METADATA
flake8_boolean_trap-1.0.1.dist-info/WHEEL
flake8_boolean_trap-1.0.1.dist-info/entry_points.txt
flake8_boolean_trap-1.0.1.dist-info/RECORD
