Metadata-Version: 2.1
Name: flake8-boolean-trap
Version: 1.0.1
Summary: flake8 plugin which forbids boolean positional arguments
Home-page: https://pwoolvett.github.io/flake8_boolean_trap
License: Unlicense
Author: Pablo Woolvett
Author-email: github@devx.pw
Requires-Python: >=3.8,<4.0
Classifier: Environment :: Console
Classifier: Framework :: Flake8
Classifier: Intended Audience :: Developers
Classifier: License :: Other/Proprietary License
Classifier: Programming Language :: Python :: 3
Classifier: Programming Language :: Python :: 3.8
Classifier: Programming Language :: Python :: 3.9
Classifier: Programming Language :: Python :: 3.10
Classifier: Programming Language :: Python :: 3.11
Classifier: Programming Language :: Python :: 3 :: Only
Classifier: Programming Language :: Python :: Implementation :: CPython
Classifier: Topic :: Software Development :: Libraries :: Python Modules
Classifier: Topic :: Software Development :: Quality Assurance
Requires-Dist: flake8
Project-URL: Repository, https://github.com/pwoolvett/flake8_boolean_trap
